mkdocs_toc_md/__init__.py
mkdocs_toc_md/hook.py
mkdocs_toc_md/objects.py
mkdocs_toc_md/plugin.py
mkdocs_toc_md/template/toc.md.j2
mkdocs_toc_md-0.0.9.dist-info/LICENSE
mkdocs_toc_md-0.0.9.dist-info/METADATA
mkdocs_toc_md-0.0.9.dist-info/WHEEL
mkdocs_toc_md-0.0.9.dist-info/entry_points.txt
mkdocs_toc_md-0.0.9.dist-info/top_level.txt
mkdocs_toc_md-0.0.9.dist-info/RECORD
