Metadata-Version: 2.1
Name: mkdocs-toc-md
Version: 0.0.9
Summary: Generate a table of contents markdown file
Home-page: https://github.com/try0/mkdocs-toc-md
Author: Ryo Tsunoda
Author-email: try0.development@gmail.com
License: MIT
Keywords: mkdocs plugin toc generator
Platform: UNKNOWN
Classifier: Development Status :: 3 - Alpha
Classifier: Intended Audience :: Developers
Classifier: Intended Audience :: Information Technology
Classifier: License :: OSI Approved :: MIT License
Classifier: Programming Language :: Python :: 3
Classifier: Topic :: Documentation
Classifier: Topic :: Software Development :: Documentation
Requires-Python: >=3.6
License-File: LICENSE
Requires-Dist: beautifulsoup4 (>=4.6.3)
Requires-Dist: mkdocs (>=1.1)
